crypticbcs/__init__.py
crypticbcs-0.3.dist-info/METADATA
crypticbcs-0.3.dist-info/WHEEL
crypticbcs-0.3.dist-info/licence.txt
crypticbcs-0.3.dist-info/top_level.txt
crypticbcs-0.3.dist-info/RECORD
